test_SW/Smith_Waterman.py
test_SW/__init__.py
test_SW-0.0.1.dist-info/METADATA
test_SW-0.0.1.dist-info/WHEEL
test_SW-0.0.1.dist-info/top_level.txt
test_SW-0.0.1.dist-info/RECORD
