Metadata-Version: 2.1
Name: test-SW
Version: 0.0.1
Summary: Just practice,about Smith_Waterman
Author: zero__to_one
Author-email: tanghao0526@163.com
License: MIT
